peak_finder/__init__.py
peak_finder/automatic.py
peak_finder/automatic_no_ml.py
peak_finder/background_removal.py
peak_finder/classify_data.py
peak_finder/data_spy.py
peak_finder/efficient_data_generation.py
peak_finder/fit_lorentz.py
peak_finder/generate_data.py
peak_finder/generate_lorentz.py
peak_finder/sliding_window.py
peak_finder/track_peaks.py
peak_finder/train_model.py
peak_finder/live_fitting/__init__.py
peak_finder/live_fitting/live_fitting.py
peak_finder/scripts/__init__.py
peak_finder/scripts/multi_class_train.py
peak_finder/scripts/train_simple_class.py
peak_finder/scripts/train_simple_count.py
peak_finder/scripts/train_tight_split.py
peak_finder/scripts/train_tight_wiggle.py
peak_finder/scripts/train_wide_wiggle.py
peak_finder/utilities/__init__.py
peak_finder/utilities/utilities.py
peak_finder-0.5.2.dist-info/METADATA
peak_finder-0.5.2.dist-info/WHEEL
peak_finder-0.5.2.dist-info/top_level.txt
peak_finder-0.5.2.dist-info/RECORD
