Metadata-Version: 2.1
Name: peak-finder
Version: 0.5.2
Summary: For finding and processing Lorentzian line shapes.
Home-page: https://github.com/GabePoel/ML-Peak-Tracker
Author: Gabriel Perko-Engel
Author-email: gpe@berkeley.edu
License: MIT
Platform: UNKNOWN
Classifier: Programming Language :: Python :: 3
Classifier: License :: OSI Approved :: MIT License
Classifier: Operating System :: OS Independent
Classifier: Topic :: Scientific/Engineering :: Physics
Requires-Python: >=3/6
Requires-Dist: numpy
Requires-Dist: scipy
Requires-Dist: matplotlib
Requires-Dist: nptdms
Requires-Dist: pysimplegui
Requires-Dist: tqdm
